examples/1minimal_example.py
examples/2tests_showcase.py
examples/3recommended_setup.py
examples/4how_it_works.py
generalimport/__init__.py
generalimport/dunders.py
generalimport/exception.py
generalimport/fake_module.py
generalimport/general_importer.py
generalimport/generalimport_bottom.py
generalimport/import_catcher.py
generalimport/min.py
generalimport/top.py
generalimport/test/funcs.py
generalimport/test/test_generalimport.py
generalimport/test/test_usage/__init__.py
generalimport/test/test_usage/test_binary.py
generalimport/test/test_usage/test_callable.py
generalimport/test/test_usage/test_cast.py
generalimport/test/test_usage/test_compare.py
generalimport/test/test_usage/test_context.py
generalimport/test/test_usage/test_delete.py
generalimport/test/test_usage/test_info.py
generalimport/test/test_usage/test_iterable.py
generalimport/test/test_usage/test_logic.py
generalimport/test/test_usage/test_lookup.py
generalimport/test/test_usage/test_math.py
generalimport/test/test_usage/test_matrix.py
generalimport/test/test_usage/test_object.py
generalimport/test/test_usage/test_pickle.py
generalimport/test/test_usage/test_raise.py
generalimport/test/test_usage/test_string.py
generalimport/test/test_usage/test_thread.py
generalimport/test/test_usage/test_typing.py
generalimport-0.5.2.dist-info/LICENSE
generalimport-0.5.2.dist-info/METADATA
generalimport-0.5.2.dist-info/WHEEL
generalimport-0.5.2.dist-info/top_level.txt
generalimport-0.5.2.dist-info/RECORD
