Metadata-Version: 2.1
Name: generalimport
Version: 0.5.2
Summary: Handle all your optional dependencies with a single call!
Home-page: https://github.com/ManderaGeneral/generalimport
Author: Rickard "Mandera" Abraham
Author-email: rickard.abraham@gmail.com
License: apache2
Classifier: Programming Language :: Python :: 3.8
Classifier: Programming Language :: Python :: 3.9
Classifier: Programming Language :: Python :: 3.10
Classifier: Programming Language :: Python :: 3.11
Classifier: Programming Language :: Python :: 3.12
Classifier: License :: OSI Approved :: Apache Software License
Classifier: Operating System :: Microsoft :: Windows
Classifier: Operating System :: POSIX :: Linux
License-File: LICENSE
